finex/__init__.py
finex/financials.py
finex/ratios.py
finex-0.0.1.dist-info/LICENSE.txt
finex-0.0.1.dist-info/METADATA
finex-0.0.1.dist-info/WHEEL
finex-0.0.1.dist-info/entry_points.txt
finex-0.0.1.dist-info/top_level.txt
finex-0.0.1.dist-info/RECORD
